arclength_method/__init__.py
arclength_method/arclength_method.py
arclength_method-0.0.2.dist-info/LICENSE
arclength_method-0.0.2.dist-info/METADATA
arclength_method-0.0.2.dist-info/WHEEL
arclength_method-0.0.2.dist-info/top_level.txt
arclength_method-0.0.2.dist-info/RECORD
