Metadata-Version: 2.1
Name: arclength-method
Version: 0.0.2
Summary: Arc Length Method for non-linear FEM
Home-page: https://github.com/kosokolovskiy/FEM_studywork_3.git
Author: Konstantin Sokolovskiy
Author-email: kosokolovsky@gmail.com
License: UNKNOWN
Platform: UNKNOWN
Classifier: Programming Language :: Python :: 3.9
Classifier: License :: OSI Approved :: GNU General Public License v3 (GPLv3)
